[{"content":"前言\r我这人并不工于文字，想写的很多，写出来又常常不尽人意，所以日记、思维体操一类总被我搁置在后头，哪天想起也没有落笔的动机。\n看到Z某写的年度总结，却也耐不住，恰好不想再下床预习线代，于是就简单写了这样一篇年度总结。\n正文\r不是那么惯例的年度总结。\n按理说年度总结应从前一年的元旦起，把这365天心里想的没想过的、做过的没做过的，翻来覆去地写一遍，大纲式地列出种种已是过往的回忆，再以新年期望收尾。\n我不想按日期来划分新年，2024的故事要从23年12月13日讲起。\n2023\r5/21-12/13\n我并不想在事后为这段时光定性，但要说感受的话，这是我18年间极为美好也极为痛苦的7个月。也因此，2024要从13日晚上我打开qq的那一刻算起。\n2024\r2023/12/13-2024/1/21\n第一次翘晚自习。其实并不是第一次，翻照片发现8月也去过\n一个人坐在傍晚体育馆的二楼，看着太阳渐渐落下，看着路边的树被LED灯照的犹如樱花盛放，那番光影我此生难忘。\n此后便一头扎入九省联考的复习之中，也许是释然，也许是不甘心，但即使到了高考我也没能再找回当时的动机。 2/29\n第n次以发生物讲义之名留在大课间的教室，假装冷静的我在讲台上查到了九省联考的结果。\n3/20\n以我为参考系的地球转过了第十八个周期，真正开始收到礼物的第二年。\n在前一天惊讶于收到了三个月未曾聊天的好友的消息，在当天收到了最不值得惊讶的礼物。\n6/8 - 6/11\n高考结束，离开附中。\n7/29 - 8/18\n收到浙大的录取通知书，来到浙大。\n8/18 - 至今\n大学的第一个半年即使在我期末周不想复习的笔下也无话可说，惊觉这篇回顾似乎也是为了醋包的饺子，那我也便无言以对了。\n回望这一年，似乎做了很多，也似乎碌碌无为。做了很多题，聊了很多天，最终留下来的也不过寥寥数语。\n真味是淡，至人是常，愿2025能一直走在路上。\n2025/1/1 写于舍友正在复习只剩我在床上的宿舍\n","date":"2025-01-01T15:37:01+08:00","permalink":"http://localhost:1313/posts/2024/","title":"2024"},{"content":"","date":"0001-01-01T00:00:00Z","permalink":"http://localhost:1313/posts/","title":""}]