[{"content":"本题是由KevinTheMH写作，在公众号语谜Puzzling上发布的一道十分精彩的Puzzle。我队（ Celestial \u0026lt;Catellite\u0026gt; ）在发布17h后成功解出，获得该题三杀。个人很喜欢这道题，因此简单作一题解兼做题历程记录。\n（ 题干部分来自于语谜Puzzling公众号，原文请见 盛典启幕：The Festival Will Be Declared ） 题干部分如下：\nA pair of star-crossed lovers came to the festival. Saying sweet-ish vows about bringing down the stars and planets, their paths in life really crossed, amidst the promise of being there for each other.(Note: the couple was facing the south at this romantic moment)\n腾讯文档：盛典启幕：The Festival Will Be Declared\n首先可以看到一个十分巨大的wordsearch和旁边指示单词长度的一列数字，第一步：当然是自己完成这个wordsearch！当然是把wordsearch丢进焖肉面的solver！就可以得到下图中的结果：\n下一步也很显然：找出wordsearch中词所在的位置，并将找到的词与右侧的（ n ）相对应，在对应过程中不难注意到右侧单词都是按照字典序进行排列，可用以检查正误和定位剩余单词的前几个字母。总之用尽各种方法艰难完成wordsearch后我们会得到下图：\n在wordsearch过程中不难注意到部分关联性较强的单词，我们最早注意到的是waiting for love和without you都是英文歌曲，california和georgia都是美国州名（这里实际上有问题，我们在下一步接近完成时才在提示下改过来），但在之后并没有意识到这实际上是一个Connecting Wall，直到题目发布1h后的提示二才让我们有了新的进展。接下来自然是要把这32个词分为8类，完成这一步后表格会变成下图中这样：\n表中？？？对应的分类应为与世界四大长河之一的名字有关，五行+词应为五种古典元素+词\n这一步Connecting Wall实际上十分难以完成，特别是五行+词、Smith和与世界四大长河之一的名字有关这三个分类，在没有提示的情况下很难想得到。含有不常见分类且没有正解反馈的Connections都孬总之又在用尽各种方法后，我们完成了这个Connecting Wall，然后呢？似乎又一次没了解题方向。\n在这时可以回头看看Flavor Text，有几个关键词值得注意——sweet-ish和bringing down the stars and planets。参考提示三，前者实际上是一个常见的homophone（谐音词），也即swedish，后者则有暗示行星，二者结合可知实际上指的是瑞典太阳系模型（Swedish Solar System，即SSS），而上一步Connecting Wall中的每一个分类都与SSS中的地标有一一对应关系，搜索后表格应该会是这样：\n图中红字为做题时没有找到的地标名\n同时，FT中还提到多次crossed，也可以参考提示五，总之下一步应该提取路径交叉点的字母，提取字母后不难想到下一步应该是排序，这里有一个很自然的顺序——按照太阳系顺序对各组进行重排！这一步后表格belike：\n就会得到一句指示：SPIRALLY REARRANGE START FROM CENTER（从中心开始螺旋重排），重新回到这个wordsearch盘面，不难在中心发现congrats，提示我们螺旋重排的方向。在code后，我们可以得到新的wordsearch，其中第一行很明显的是新的指示：CONGRATS LIFT YOUR SPIRITS FOR THIS FESTIVAL，其中spirits在这题中指的是神明，参考提示七、八，我们可以找到31个神明的名字。同样地，按照其职责可以将其分为八组，每一组都以十字形（cross）环绕着中心字母，自然地提取八个字母后，我们再次面临排序的问题，类似上一次排序，八种职责可以对应太阳系中的八颗天体（参考希腊和罗马神话），再次按照太阳系顺序进行排列，我们便可得到下图中的表格：\n图中木星对应众神之主，天王星对应天空之神\n现在我们得到了一句新的指示：rot eight，即对wordsearch的盘面凯撒移位8位。移位后可以发现盘面的最下面一行变为LOOK UP ON FEB TWENTY EIGHTH THIS YEAR AT NIGHT（在今年的二月二十八日夜晚抬头），至此，本题的主题终于浮现——2025年2月28日七星连珠，沿着黄道（ecliptic），七颗行星会以火星、木星、天王星、金星、海王星、水星和土星的顺序排列。\n按照指示从盘面最底下开始向上看（look up），可以在第七行的两端发现ECLIPTIC，这就是本道题的黄道！在黄道所在行中间可以发现间距2的离散型ECLIPTIC，参考提示八，这个ECLIPTIC将黄道分为七个双字母组（bigram），刚好对应七星连珠。再一次，也是最后一次，将这七个双字母组按照太阳系顺序排列，便可得到最终答案——A FAREWELL WALTZ（告别的华尔兹）。至此这道题就全部结束了!\n来自官方题解的一张图\n官方题解请见【解析】盛典启幕：The Festival Will Be Declared\n可以看出这是一道十分精彩、十分浪漫，难度也很高的Puzzle，虽然有一点引导不足、大盘wordsearch过程略枯燥的问题，但好在提示给的很充分！跟着提示走可以解的很顺畅，事实是从领先提示到跟不上提示进度开始睡觉。以下是一些fun stuff！\n蔚蓝玩家特有的警觉\n并非mitmh\n是谁只领到3.62我不说\n","date":"2025-03-02T00:00:00Z","permalink":"http://localhost:1313/posts/puzzle-the-festival-will-be-declared/","title":"Puzzle | The Festival Will Be Declared"},{"content":"参加过的Puzzle Hunt列表\n活动名称 时间 队伍名称 队伍人数 最终名次 备注 CCBC 13\u0026amp;14（暂无静态站） 2023/08 Rosmontis 2 未完赛 Puzzle \u0026amp; Key Universe 3（上） 2024/07 天空度假旅游团 6 81 JUST Puzzle Hunt 2024/09 天空度假自驾游 3 44 几乎未参与 玥hunt 2024/10 Rosmarinus 2 103 Seco Puzzle Hunt 2025/01 Rosmarinus 1 49 原来是这样 蛇年闯关 2025/01 2 1 Cornsnaky\u0026rsquo;s Snake Year Puzzle Hunt 2025/02 Celestial \u0026lt;Catellite\u0026gt; 6 6 第三届亦乐杯 2025/02 Celestial \u0026lt;Catellite\u0026gt; 3 ~10 详细信息见下表\n","date":"2025-02-06T13:14:43+08:00","permalink":"http://localhost:1313/posts/puzzle-hunt%E8%AE%B0%E5%BD%95/","title":"Puzzle Hunt记录"}]